rad/__init__.py
rad/_version.py
rad/integration.py
rad/_parser/__init__.py
rad/_parser/_archive.py
rad/_parser/_diff.py
rad/_parser/_process.py
rad/_parser/_ssc.py
rad/_parser/_super_schema.py
rad/resources/__init__.py
rad/resources/manifests/datamodels-1.0.yaml
rad/resources/manifests/datamodels-1.1.0.yaml
rad/resources/manifests/datamodels-1.2.0.yaml
rad/resources/manifests/datamodels-1.3.0.yaml
rad/resources/manifests/datamodels-1.4.0.yaml
rad/resources/manifests/datamodels-1.5.0.yaml
rad/resources/manifests/datamodels-1.6.0.yaml
rad/resources/manifests/datamodels-1.7.0.yaml
rad/resources/manifests/static-1.0.0.yaml
rad/resources/manifests/static-1.1.0.yaml
rad/resources/schemas/associations-1.0.0.yaml
rad/resources/schemas/basic-1.0.0.yaml
rad/resources/schemas/basic-1.1.0.yaml
rad/resources/schemas/cal_logs-1.0.0.yaml
rad/resources/schemas/cal_step_flag-1.0.0.yaml
rad/resources/schemas/common-1.0.0.yaml
rad/resources/schemas/common-1.1.0.yaml
rad/resources/schemas/common-1.2.0.yaml
rad/resources/schemas/common-1.3.0.yaml
rad/resources/schemas/common-1.4.0.yaml
rad/resources/schemas/coordinates-1.0.0.yaml
rad/resources/schemas/ephemeris-1.0.0.yaml
rad/resources/schemas/ephemeris-1.1.0.yaml
rad/resources/schemas/exposure-1.0.0.yaml
rad/resources/schemas/exposure-1.1.0.yaml
rad/resources/schemas/exposure-1.2.0.yaml
rad/resources/schemas/exposure-1.3.0.yaml
rad/resources/schemas/exposure_type-1.0.0.yaml
rad/resources/schemas/exposure_type-1.1.0.yaml
rad/resources/schemas/exposure_type-1.2.0.yaml
rad/resources/schemas/forced_catalog_table-1.0.0.yaml
rad/resources/schemas/forced_image_source_catalog-1.0.0.yaml
rad/resources/schemas/forced_image_source_catalog-1.1.0.yaml
rad/resources/schemas/forced_image_source_catalog-1.2.0.yaml
rad/resources/schemas/forced_mosaic_source_catalog-1.0.0.yaml
rad/resources/schemas/forced_mosaic_source_catalog-1.1.0.yaml
rad/resources/schemas/forced_mosaic_source_catalog-1.2.0.yaml
rad-0.29.1.dist-info/licenses/LICENSE
rad-0.29.1.dist-info/METADATA
rad-0.29.1.dist-info/WHEEL
rad-0.29.1.dist-info/entry_points.txt
rad-0.29.1.dist-info/top_level.txt
rad-0.29.1.dist-info/RECORD
