Metadata-Version: 2.4
Name: rad
Version: 0.29.1
Summary: Roman Attribute Dictionary
Author: STScI
Project-URL: Bug Tracker, https://github.com/spacetelescope/rad/issues
Project-URL: Source Code, https://github.com/spacetelescope/rad
Classifier: Intended Audience :: Science/Research
Classifier: Topic :: Scientific/Engineering :: Astronomy
Classifier: Programming Language :: Python :: 3
Requires-Python: >=3.11
License-File: LICENSE
Requires-Dist: asdf>=4.1.0
Requires-Dist: asdf-astropy>=0.8.0
Provides-Extra: test
Requires-Dist: pytest>=7.0.0; extra == "test"
Requires-Dist: pytest-doctestplus>=1.2.1; extra == "test"
Requires-Dist: pytest-asdf-plugin>=0.1.0; extra == "test"
Requires-Dist: crds>=12.0.4; extra == "test"
Requires-Dist: GitPython>=3.1.44; extra == "test"
Requires-Dist: semantic-version>=2.10.0; extra == "test"
Requires-Dist: textual>=3.1; extra == "test"
Requires-Dist: deepdiff>=8.1; extra == "test"
Provides-Extra: docs
Requires-Dist: sphinx; extra == "docs"
Requires-Dist: sphinx-asdf>=0.1.3; extra == "docs"
Requires-Dist: sphinx-astropy; extra == "docs"
Requires-Dist: sphinx-rtd-theme; extra == "docs"
Requires-Dist: astropy>=5.0.4; extra == "docs"
Requires-Dist: graphviz; extra == "docs"
Requires-Dist: matplotlib; extra == "docs"
Requires-Dist: docutils; extra == "docs"
Requires-Dist: importlib-metadata; extra == "docs"
Requires-Dist: towncrier; extra == "docs"
Dynamic: license-file
